Examples/ff_A20/src/ffr_A20.sv
`timescale 1ns/1ps
module ffr_A20
             #(parameter w = 2)
             (input logic clk,
             input logic [w-1:0] d,
             output logic [w-1:0] q);

             always_ff @(posedge clk)
               q <= d;

endmodule

Examples/ff_A20/ffr_A20.vcd
$date
	Mon Sep 13 23:00:59 2021
$end
$version
	Icarus Verilog
$end
$timescale
	1ps
$end
$scope module ffr_A20 $end
$var wire 1 ! clk $end
$var wire 2 " d [1:0] $end
$var reg 2 # q [1:0] $end
$upscope $end
$enddefinitions $end
#0
$dumpvars
b1 #
b1 "
1!
$end
#5000000
b0 "
0!
#10000000
b0 #
1!
#15000000
b1 "
0!
#20000000
b1 #
1!
#25000000
0!
#30000000
1!
#35000000
b0 "
0!
#40000000
b0 #
1!
#45000000
0!
#50000000
1!
#55000000
0!
#60000000
1!
#65000000
b1 "
0!
#70000000
b1 #
1!
#75000000
b0 "
0!
#80000000
b0 #
1!
